{
    "sourceFile": "package.json",
    "activeCommit": 0,
    "commits": [
        {
            "activePatchIndex": 0,
            "patches": [
                {
                    "date": 1775624580061,
                    "content": "Index: \n===================================================================\n--- \n+++ \n"
                }
            ],
            "date": 1775624580061,
            "name": "Commit-0",
            "content": "{\n  \"devDependencies\": {\n    \"javascript-obfuscator\": \"^5.4.1\"\n  },\n  \"name\": \"drinkordoom_v\",\n  \"version\": \"1.0.0\",\n  \"description\": \"\",\n  \"main\": \"index.js\",\n  \"dependencies\": {\n    \"acorn\": \"^8.15.0\",\n    \"acorn-import-attributes\": \"^1.9.5\",\n    \"ansi-styles\": \"^4.3.0\",\n    \"array-differ\": \"^3.0.0\",\n    \"array-union\": \"^2.1.0\",\n    \"arrify\": \"^2.0.1\",\n    \"assert\": \"^2.1.0\",\n    \"async-retry\": \"^1.3.3\",\n    \"available-typed-arrays\": \"^1.0.7\",\n    \"balanced-match\": \"^1.0.2\",\n    \"brace-expansion\": \"^1.1.13\",\n    \"call-bind\": \"^1.0.8\",\n    \"call-bind-apply-helpers\": \"^1.0.2\",\n    \"call-bound\": \"^1.0.4\",\n    \"chalk\": \"^4.1.2\",\n    \"chance\": \"^1.1.13\",\n    \"char-regex\": \"^1.0.2\",\n    \"charenc\": \"^0.0.2\",\n    \"class-validator\": \"^0.14.3\",\n    \"color-convert\": \"^2.0.1\",\n    \"color-name\": \"^1.1.4\",\n    \"commander\": \"^12.1.0\",\n    \"concat-map\": \"^0.0.1\",\n    \"crypt\": \"^0.0.2\",\n    \"deep-is\": \"^0.1.4\",\n    \"define-data-property\": \"^1.1.4\",\n    \"define-properties\": \"^1.2.1\",\n    \"dunder-proto\": \"^1.0.1\",\n    \"env-paths\": \"^4.0.0\",\n    \"es-define-property\": \"^1.0.1\",\n    \"es-errors\": \"^1.3.0\",\n    \"es-object-atoms\": \"^1.1.1\",\n    \"eslint-scope\": \"^8.4.0\",\n    \"eslint-visitor-keys\": \"^4.2.1\",\n    \"esprima\": \"^4.0.1\",\n    \"esrecurse\": \"^4.3.0\",\n    \"estraverse\": \"^5.3.0\",\n    \"esutils\": \"^2.0.3\",\n    \"fast-deep-equal\": \"^3.1.3\",\n    \"fast-levenshtein\": \"^2.0.6\",\n    \"for-each\": \"^0.3.5\",\n    \"function-bind\": \"^1.1.2\",\n    \"generator-function\": \"^2.0.1\",\n    \"get-intrinsic\": \"^1.3.0\",\n    \"get-proto\": \"^1.0.1\",\n    \"gopd\": \"^1.2.0\",\n    \"has-flag\": \"^4.0.0\",\n    \"has-property-descriptors\": \"^1.0.2\",\n    \"has-symbols\": \"^1.1.0\",\n    \"has-tostringtag\": \"^1.0.2\",\n    \"hasown\": \"^2.0.2\",\n    \"inherits\": \"^2.0.4\",\n    \"inversify\": \"^6.1.4\",\n    \"is-arguments\": \"^1.2.0\",\n    \"is-buffer\": \"^2.0.5\",\n    \"is-callable\": \"^1.2.7\",\n    \"is-generator-function\": \"^1.1.2\",\n    \"is-nan\": \"^1.3.2\",\n    \"is-node-process\": \"^1.2.0\",\n    \"is-regex\": \"^1.2.1\",\n    \"is-safe-filename\": \"^0.1.1\",\n    \"is-typed-array\": \"^1.1.15\",\n    \"js-string-escape\": \"^1.0.1\",\n    \"levn\": \"^0.3.0\",\n    \"libphonenumber-js\": \"^1.12.41\",\n    \"math-intrinsics\": \"^1.1.0\",\n    \"md5\": \"^2.3.0\",\n    \"minimatch\": \"^3.1.5\",\n    \"multimatch\": \"^5.0.0\",\n    \"object-is\": \"^1.1.6\",\n    \"object-keys\": \"^1.1.1\",\n    \"object.assign\": \"^4.1.7\",\n    \"optionator\": \"^0.8.3\",\n    \"possible-typed-array-names\": \"^1.1.0\",\n    \"prelude-ls\": \"^1.1.2\",\n    \"process\": \"^0.11.10\",\n    \"reflect-metadata\": \"^0.2.2\",\n    \"retry\": \"^0.13.1\",\n    \"safe-regex-test\": \"^1.1.0\",\n    \"set-function-length\": \"^1.2.2\",\n    \"source-map\": \"^0.6.1\",\n    \"string-template\": \"^1.0.0\",\n    \"stringz\": \"^2.1.0\",\n    \"supports-color\": \"^7.2.0\",\n    \"throttleit\": \"^2.1.0\",\n    \"tslib\": \"^2.8.1\",\n    \"type-check\": \"^0.3.2\",\n    \"undici\": \"^6.24.1\",\n    \"util\": \"^0.12.5\",\n    \"validator\": \"^13.15.35\",\n    \"which-typed-array\": \"^1.1.20\",\n    \"word-wrap\": \"^1.2.5\"\n  },\n\"scripts\": {\n  \"test\": \"echo \\\"Error: no test specified\\\" && exit 1\",\n  \"obfuscate\": \"javascript-obfuscator js/ --output dist/js --config obfuscator.config.json\"\n},\n  \"repository\": {\n    \"type\": \"git\",\n    \"url\": \"git+https://github.com/nuthiokhaw99/Drink-or-Doom.github.io.git\"\n  },\n  \"keywords\": [],\n  \"author\": \"\",\n  \"license\": \"ISC\",\n  \"type\": \"commonjs\",\n  \"bugs\": {\n    \"url\": \"https://github.com/nuthiokhaw99/Drink-or-Doom.github.io/issues\"\n  },\n  \"homepage\": \"https://github.com/nuthiokhaw99/Drink-or-Doom.github.io#readme\"\n}\n"
        }
    ]
}