{
    "sourceFile": "js/api.js",
    "activeCommit": 0,
    "commits": [
        {
            "activePatchIndex": 8,
            "patches": [
                {
                    "date": 1774366410049,
                    "content": "Index: \n===================================================================\n--- \n+++ \n"
                },
                {
                    "date": 1774366417162,
                    "content": "Index: \n===================================================================\n--- \n+++ \n@@ -1,7 +1,5 @@\n-api.js\r\n-\r\n-```javascript\r\n+javascript\r\n /* =========================================\r\n    api.js — Google Sheets / API Integration\r\n    ========================================= */\r\n \r\n@@ -83,5 +81,4 @@\n       renderDecks();\r\n     })\r\n     .catch(() => toast('เชื่อมต่อไม่ได้ — ตรวจสอบ URL และ Share settings', 'error'));\r\n }\r\n-```\n\\ No newline at end of file\n"
                },
                {
                    "date": 1774366602700,
                    "content": "Index: \n===================================================================\n--- \n+++ \n@@ -1,8 +1,4 @@\n-javascript\r\n-/* =========================================\r\n-   api.js — Google Sheets / API Integration\r\n-   ========================================= */\r\n \r\n const API = {\r\n   sheetUrl: localStorage.getItem('ds_sheet_url') || '',\r\n \r\n"
                },
                {
                    "date": 1774567467368,
                    "content": "Index: \n===================================================================\n--- \n+++ \n@@ -1,21 +1,18 @@\n-\r\n const API = {\r\n   sheetUrl: localStorage.getItem('ds_sheet_url') || '',\r\n \r\n   setSheetUrl(url) {\r\n     this.sheetUrl = url;\r\n     localStorage.setItem('ds_sheet_url', url);\r\n   },\r\n \r\n-  /* แปลง Google Sheets URL → JSON export URL */\r\n   toJsonUrl(sheetUrl, sheetIndex = 0) {\r\n     const match = sheetUrl.match(/\\/d\\/([a-zA-Z0-9-_]+)/);\r\n     if (!match) return null;\r\n     return `https://docs.google.com/spreadsheets/d/${match[1]}/gviz/tq?tqx=out:json&sheet=${sheetIndex}`;\r\n   },\r\n \r\n-  /* ดึงข้อมูล Sheets แล้ว parse เป็น array of objects */\r\n   async fetchSheet(sheetUrl, sheetName = '') {\r\n     try {\r\n       const match = sheetUrl.match(/\\/d\\/([a-zA-Z0-9-_]+)/);\r\n       if (!match) throw new Error('URL ไม่ถูกต้อง');\r\n@@ -34,9 +31,8 @@\n       throw e;\r\n     }\r\n   },\r\n \r\n-  /* โหลด decks + cards จาก Sheets แล้วอัพเดต DB */\r\n   async syncFromSheets(url) {\r\n     const decksRaw = await this.fetchSheet(url, 'decks');\r\n     const cardsRaw = await this.fetchSheet(url, 'cards');\r\n \r\n@@ -57,8 +53,62 @@\n     });\r\n \r\n     saveDB();\r\n     return { decks: DB.decks.length, cards: cardsRaw.length };\r\n+  },\r\n+\r\n+  /* =========================================\r\n+     CREDITS — Supabase\r\n+     ========================================= */\r\n+\r\n+  /** ดึงเครดิตของ user ปัจจุบันจาก Supabase */\r\n+  async getCredits() {\r\n+    if (!currentUser) return 0;\r\n+    const { data, error } = await _sb\r\n+      .from('profiles')\r\n+      .select('credits')\r\n+      .eq('id', currentUser.id)\r\n+      .single();\r\n+    if (error) { console.error('getCredits error:', error); return 0; }\r\n+    return data?.credits ?? 0;\r\n+  },\r\n+\r\n+  /** บันทึกเครดิตลง Supabase */\r\n+  async saveCredits(amount) {\r\n+    if (!currentUser) return;\r\n+    const { error } = await _sb\r\n+      .from('profiles')\r\n+      .update({ credits: amount })\r\n+      .eq('id', currentUser.id);\r\n+    if (error) console.error('saveCredits error:', error);\r\n+  },\r\n+\r\n+  /** เพิ่มเครดิต (อ่านค่าเดิมก่อน แล้วบวกเพิ่ม) */\r\n+  async addCredits(amount) {\r\n+    const current = await this.getCredits();\r\n+    const newVal  = current + amount;\r\n+    await this.saveCredits(newVal);\r\n+    return newVal;\r\n+  },\r\n+\r\n+  /** แอดมินตั้งเครดิต user คนอื่น */\r\n+  async adminSetCredits(userId, amount) {\r\n+    const { error } = await _sb\r\n+      .from('profiles')\r\n+      .update({ credits: amount })\r\n+      .eq('id', userId);\r\n+    if (error) { console.error('adminSetCredits error:', error); return false; }\r\n+    return true;\r\n+  },\r\n+\r\n+  /** ดึง user ทั้งหมด (สำหรับแอดมิน) */\r\n+  async getAllUsers() {\r\n+    const { data, error } = await _sb\r\n+      .from('profiles')\r\n+      .select('id, username, credits, is_admin')\r\n+      .order('username');\r\n+    if (error) { console.error('getAllUsers error:', error); return []; }\r\n+    return data || [];\r\n   }\r\n };\r\n \r\n /* ---- UI handler ---- */\r\n@@ -76,5 +126,5 @@\n       renderAdmSel();\r\n       renderDecks();\r\n     })\r\n     .catch(() => toast('เชื่อมต่อไม่ได้ — ตรวจสอบ URL และ Share settings', 'error'));\r\n-}\r\n+}\n\\ No newline at end of file\n"
                },
                {
                    "date": 1774651463556,
                    "content": "Index: \n===================================================================\n--- \n+++ \n@@ -100,16 +100,16 @@\n     return true;\r\n   },\r\n \r\n   /** ดึง user ทั้งหมด (สำหรับแอดมิน) */\r\n-  async getAllUsers() {\r\n-    const { data, error } = await _sb\r\n-      .from('profiles')\r\n-      .select('id, username, credits, is_admin')\r\n-      .order('username');\r\n-    if (error) { console.error('getAllUsers error:', error); return []; }\r\n-    return data || [];\r\n-  }\r\n+async getAllUsers() {\r\n+  const { data, error } = await _sb\r\n+    .from('profiles')\r\n+    .select('id, username, credits, is_admin, is_banned, last_seen')\r\n+    .order('created_at', { ascending: false });\r\n+  if (error) { console.error(error); return []; }\r\n+  return data;\r\n+}\r\n };\r\n \r\n /* ---- UI handler ---- */\r\n function connectSheet() {\r\n"
                },
                {
                    "date": 1774652195821,
                    "content": "Index: \n===================================================================\n--- \n+++ \n@@ -104,9 +104,9 @@\n async getAllUsers() {\r\n   const { data, error } = await _sb\r\n     .from('profiles')\r\n     .select('id, username, credits, is_admin, is_banned, last_seen')\r\n-    .order('created_at', { ascending: false });\r\n+    .order('id', { ascending: false });\r\n   if (error) { console.error(error); return []; }\r\n   return data;\r\n }\r\n };\r\n"
                },
                {
                    "date": 1774905719274,
                    "content": "Index: \n===================================================================\n--- \n+++ \n@@ -1,10 +1,11 @@\n const API = {\r\n-  sheetUrl: localStorage.getItem('ds_sheet_url') || '',\r\n+  // [FIX #19] ไม่เก็บ sheet URL ใน localStorage — ใช้แค่ใน memory session\r\n+  sheetUrl: '',\r\n \r\n   setSheetUrl(url) {\r\n     this.sheetUrl = url;\r\n-    localStorage.setItem('ds_sheet_url', url);\r\n+    // ไม่ localStorage.setItem แล้ว — ป้องกัน URL admin รั่วบน shared computer\r\n   },\r\n \r\n   toJsonUrl(sheetUrl, sheetIndex = 0) {\r\n     const match = sheetUrl.match(/\\/d\\/([a-zA-Z0-9-_]+)/);\r\n@@ -59,9 +60,8 @@\n   /* =========================================\r\n      CREDITS — Supabase\r\n      ========================================= */\r\n \r\n-  /** ดึงเครดิตของ user ปัจจุบันจาก Supabase */\r\n   async getCredits() {\r\n     if (!currentUser) return 0;\r\n     const { data, error } = await _sb\r\n       .from('profiles')\r\n@@ -71,9 +71,8 @@\n     if (error) { console.error('getCredits error:', error); return 0; }\r\n     return data?.credits ?? 0;\r\n   },\r\n \r\n-  /** บันทึกเครดิตลง Supabase */\r\n   async saveCredits(amount) {\r\n     if (!currentUser) return;\r\n     const { error } = await _sb\r\n       .from('profiles')\r\n@@ -81,17 +80,60 @@\n       .eq('id', currentUser.id);\r\n     if (error) console.error('saveCredits error:', error);\r\n   },\r\n \r\n-  /** เพิ่มเครดิต (อ่านค่าเดิมก่อน แล้วบวกเพิ่ม) */\r\n   async addCredits(amount) {\r\n     const current = await this.getCredits();\r\n     const newVal  = current + amount;\r\n     await this.saveCredits(newVal);\r\n     return newVal;\r\n   },\r\n \r\n-  /** แอดมินตั้งเครดิต user คนอื่น */\r\n+  /* =========================================\r\n+     [FIX #5] Atomic credit deduction ผ่าน Supabase RPC\r\n+     ป้องกัน race condition เมื่อกดไพ่หลายใบพร้อมกัน\r\n+     \r\n+     ต้องสร้าง function นี้บน Supabase SQL Editor:\r\n+     \r\n+     CREATE OR REPLACE FUNCTION deduct_credits(user_id uuid, amount integer)\r\n+     RETURNS integer\r\n+     LANGUAGE plpgsql SECURITY DEFINER AS $$\r\n+     DECLARE\r\n+       current_credits integer;\r\n+       new_credits integer;\r\n+     BEGIN\r\n+       SELECT credits INTO current_credits FROM profiles WHERE id = user_id FOR UPDATE;\r\n+       IF current_credits < amount THEN\r\n+         RETURN -1; -- ไม่พอ\r\n+       END IF;\r\n+       new_credits := current_credits - amount;\r\n+       UPDATE profiles SET credits = new_credits WHERE id = user_id;\r\n+       RETURN new_credits;\r\n+     END;\r\n+     $$;\r\n+     ========================================= */\r\n+  async deductCredits(amount) {\r\n+    if (!currentUser) return { success: false, newBalance: 0 };\r\n+\r\n+    const { data, error } = await _sb.rpc('deduct_credits', {\r\n+      user_id: currentUser.id,\r\n+      amount:  amount\r\n+    });\r\n+\r\n+    if (error) {\r\n+      console.error('deductCredits error:', error);\r\n+      // fallback: ถ้า RPC ยังไม่ได้สร้าง ใช้วิธีเดิมชั่วคราว\r\n+      const current = await this.getCredits();\r\n+      if (current < amount) return { success: false, newBalance: current };\r\n+      const newVal = current - amount;\r\n+      await this.saveCredits(newVal);\r\n+      return { success: true, newBalance: newVal };\r\n+    }\r\n+\r\n+    if (data === -1) return { success: false, newBalance: await this.getCredits() };\r\n+    return { success: true, newBalance: data };\r\n+  },\r\n+\r\n   async adminSetCredits(userId, amount) {\r\n     const { error } = await _sb\r\n       .from('profiles')\r\n       .update({ credits: amount })\r\n@@ -99,17 +141,16 @@\n     if (error) { console.error('adminSetCredits error:', error); return false; }\r\n     return true;\r\n   },\r\n \r\n-  /** ดึง user ทั้งหมด (สำหรับแอดมิน) */\r\n-async getAllUsers() {\r\n-  const { data, error } = await _sb\r\n-    .from('profiles')\r\n-    .select('id, username, credits, is_admin, is_banned, last_seen')\r\n-    .order('id', { ascending: false });\r\n-  if (error) { console.error(error); return []; }\r\n-  return data;\r\n-}\r\n+  async getAllUsers() {\r\n+    const { data, error } = await _sb\r\n+      .from('profiles')\r\n+      .select('id, username, credits, is_admin, is_banned, last_seen')\r\n+      .order('id', { ascending: false });\r\n+    if (error) { console.error(error); return []; }\r\n+    return data;\r\n+  }\r\n };\r\n \r\n /* ---- UI handler ---- */\r\n function connectSheet() {\r\n"
                },
                {
                    "date": 1775213931127,
                    "content": "Index: \n===================================================================\n--- \n+++ \n@@ -151,21 +151,5 @@\n     return data;\r\n   }\r\n };\r\n \r\n-/* ---- UI handler ---- */\r\n-function connectSheet() {\r\n-  const url = document.getElementById('sheet-url').value.trim();\r\n-  if (!url) { toast('กรุณาใส่ URL', 'warning'); return; }\r\n-\r\n-  API.setSheetUrl(url);\r\n-  toast('กำลังดึงข้อมูล...', 'info');\r\n-\r\n-  API.syncFromSheets(url)\r\n-    .then(({ decks, cards }) => {\r\n-      toast(`โหลดสำเร็จ! ${decks} กอง, ${cards} ใบ`, 'success');\r\n-      renderAdmDecks();\r\n-      renderAdmSel();\r\n-      renderDecks();\r\n-    })\r\n-    .catch(() => toast('เชื่อมต่อไม่ได้ — ตรวจสอบ URL และ Share settings', 'error'));\r\n-}\n\\ No newline at end of file\n+// connectSheet() นิยามใน admin.js — ห้ามเพิ่มที่นี่อีก\n\\ No newline at end of file\n"
                },
                {
                    "date": 1775236365116,
                    "content": "Index: \n===================================================================\n--- \n+++ \n@@ -149,7 +149,9 @@\n       .order('id', { ascending: false });\r\n     if (error) { console.error(error); return []; }\r\n     return data;\r\n   }\r\n-};\r\n-\r\n-// connectSheet() นิยามใน admin.js — ห้ามเพิ่มที่นี่อีก\n\\ No newline at end of file\n+// <<<<<<< HEAD\r\n+// };\r\n+// =======\r\n+// };\r\n+// >>>>>>> 35c8474b63db1f7722e0f8c3738916b5f76e4a23\r\n"
                }
            ],
            "date": 1774366410049,
            "name": "Commit-0",
            "content": "api.js\r\n\r\n```javascript\r\n/* =========================================\r\n   api.js — Google Sheets / API Integration\r\n   ========================================= */\r\n\r\nconst API = {\r\n  sheetUrl: localStorage.getItem('ds_sheet_url') || '',\r\n\r\n  setSheetUrl(url) {\r\n    this.sheetUrl = url;\r\n    localStorage.setItem('ds_sheet_url', url);\r\n  },\r\n\r\n  /* แปลง Google Sheets URL → JSON export URL */\r\n  toJsonUrl(sheetUrl, sheetIndex = 0) {\r\n    const match = sheetUrl.match(/\\/d\\/([a-zA-Z0-9-_]+)/);\r\n    if (!match) return null;\r\n    return `https://docs.google.com/spreadsheets/d/${match[1]}/gviz/tq?tqx=out:json&sheet=${sheetIndex}`;\r\n  },\r\n\r\n  /* ดึงข้อมูล Sheets แล้ว parse เป็น array of objects */\r\n  async fetchSheet(sheetUrl, sheetName = '') {\r\n    try {\r\n      const match = sheetUrl.match(/\\/d\\/([a-zA-Z0-9-_]+)/);\r\n      if (!match) throw new Error('URL ไม่ถูกต้อง');\r\n      const url = `https://docs.google.com/spreadsheets/d/${match[1]}/gviz/tq?tqx=out:json&sheet=${encodeURIComponent(sheetName)}`;\r\n      const res  = await fetch(url);\r\n      const text = await res.text();\r\n      const json = JSON.parse(text.replace(/^[^{]+/, '').replace(/[^}]+$/, ''));\r\n      const cols = json.table.cols.map(c => c.label);\r\n      return json.table.rows.map(row => {\r\n        const obj = {};\r\n        row.c.forEach((cell, i) => { obj[cols[i]] = cell ? cell.v : ''; });\r\n        return obj;\r\n      });\r\n    } catch (e) {\r\n      console.error('fetchSheet error:', e);\r\n      throw e;\r\n    }\r\n  },\r\n\r\n  /* โหลด decks + cards จาก Sheets แล้วอัพเดต DB */\r\n  async syncFromSheets(url) {\r\n    const decksRaw = await this.fetchSheet(url, 'decks');\r\n    const cardsRaw = await this.fetchSheet(url, 'cards');\r\n\r\n    DB.decks = decksRaw.map(r => ({\r\n      id:   r.id   || ('d' + Date.now()),\r\n      name: r.name || 'ไม่มีชื่อ',\r\n      icon: r.icon || 'fi-sr-flame',\r\n      theme:r.theme || 'default',\r\n      cost: parseInt(r.cost_per_card) || 1,\r\n      desc: r.description || ''\r\n    }));\r\n\r\n    DB.cards = {};\r\n    DB.decks.forEach(d => { DB.cards[d.id] = []; });\r\n    cardsRaw.forEach(r => {\r\n      const did = r.deck_id;\r\n      if (DB.cards[did]) DB.cards[did].push({ cat: r.category || 'ทั่วไป', text: r.text || '' });\r\n    });\r\n\r\n    saveDB();\r\n    return { decks: DB.decks.length, cards: cardsRaw.length };\r\n  }\r\n};\r\n\r\n/* ---- UI handler ---- */\r\nfunction connectSheet() {\r\n  const url = document.getElementById('sheet-url').value.trim();\r\n  if (!url) { toast('กรุณาใส่ URL', 'warning'); return; }\r\n\r\n  API.setSheetUrl(url);\r\n  toast('กำลังดึงข้อมูล...', 'info');\r\n\r\n  API.syncFromSheets(url)\r\n    .then(({ decks, cards }) => {\r\n      toast(`โหลดสำเร็จ! ${decks} กอง, ${cards} ใบ`, 'success');\r\n      renderAdmDecks();\r\n      renderAdmSel();\r\n      renderDecks();\r\n    })\r\n    .catch(() => toast('เชื่อมต่อไม่ได้ — ตรวจสอบ URL และ Share settings', 'error'));\r\n}\r\n```"
        }
    ]
}